invenio_administration/__init__.py
invenio_administration/admin.py
invenio_administration/config.py
invenio_administration/decorators.py
invenio_administration/errors.py
invenio_administration/ext.py
invenio_administration/generators.py
invenio_administration/marshmallow_utils.py
invenio_administration/permissions.py
invenio_administration/webpack.py
invenio_administration/assets/semantic-ui/js/invenio_administration/.eslintrc.yml
invenio_administration/assets/semantic-ui/js/invenio_administration/.prettierrc
invenio_administration/assets/semantic-ui/js/invenio_administration/index.js
invenio_administration/assets/semantic-ui/js/invenio_administration/package.json
invenio_administration/assets/semantic-ui/js/invenio_administration/src/index.js
invenio_administration/assets/semantic-ui/js/invenio_administration/src/routes.js
invenio_administration/assets/semantic-ui/js/invenio_administration/src/theme.js
invenio_administration/assets/semantic-ui/js/invenio_administration/src/actions/ActionModal.js
invenio_administration/assets/semantic-ui/js/invenio_administration/src/actions/Actions.js
invenio_administration/assets/semantic-ui/js/invenio_administration/src/actions/Delete.js
invenio_administration/assets/semantic-ui/js/invenio_administration/src/actions/DeleteModal.js
invenio_administration/assets/semantic-ui/js/invenio_administration/src/actions/DeleteModalTrigger.js
invenio_administration/assets/semantic-ui/js/invenio_administration/src/actions/Edit.js
invenio_administration/assets/semantic-ui/js/invenio_administration/src/actions/ResourceActions.js
invenio_administration/assets/semantic-ui/js/invenio_administration/src/actions/index.js
invenio_administration/assets/semantic-ui/js/invenio_administration/src/api/actions.js
invenio_administration/assets/semantic-ui/js/invenio_administration/src/api/index.js
invenio_administration/assets/semantic-ui/js/invenio_administration/src/api/routes.js
invenio_administration-5.0.0.dist-info/licenses/AUTHORS.rst
invenio_administration-5.0.0.dist-info/licenses/LICENSE
invenio_administration-5.0.0.dist-info/METADATA
invenio_administration-5.0.0.dist-info/WHEEL
invenio_administration-5.0.0.dist-info/entry_points.txt
invenio_administration-5.0.0.dist-info/top_level.txt
invenio_administration-5.0.0.dist-info/RECORD
